<annotation>
	<folder>Images</folder>
	<filename>conference-online-registration-form.jpg</filename>
	<path>C:\Work\Inno_Vision_X\Images\conference-online-registration-form.jpg</path>
	<source>
		<database>Unknown</database>
	</source>
	<size>
		<width>650</width>
		<height>800</height>
		<depth>3</depth>
	</size>
	<segmented>0</segmented>
	<object>
		<name>textbox</name>
		<pose>Unspecified</pose>
		<truncated>0</truncated>
		<difficult>0</difficult>
		<bndbox>
			<xmin>185</xmin>
			<ymin>134</ymin>
			<xmax>296</xmax>
			<ymax>185</ymax>
		</bndbox>
	</object>
	<object>
		<name>dropdown</name>
		<pose>Unspecified</pose>
		<truncated>0</truncated>
		<difficult>0</difficult>
		<bndbox>
			<xmin>177</xmin>
			<ymin>212</ymin>
			<xmax>354</xmax>
			<ymax>261</ymax>
		</bndbox>
	</object>
	<object>
		<name>dropdown</name>
		<pose>Unspecified</pose>
		<truncated>0</truncated>
		<difficult>0</difficult>
		<bndbox>
			<xmin>351</xmin>
			<ymin>429</ymin>
			<xmax>528</xmax>
			<ymax>477</ymax>
		</bndbox>
	</object>
	<object>
		<name>textbox</name>
		<pose>Unspecified</pose>
		<truncated>0</truncated>
		<difficult>0</difficult>
		<bndbox>
			<xmin>177</xmin>
			<ymin>508</ymin>
			<xmax>458</xmax>
			<ymax>556</ymax>
		</bndbox>
	</object>
	<object>
		<name>textbox</name>
		<pose>Unspecified</pose>
		<truncated>0</truncated>
		<difficult>0</difficult>
		<bndbox>
			<xmin>181</xmin>
			<ymin>567</ymin>
			<xmax>348</xmax>
			<ymax>607</ymax>
		</bndbox>
	</object>
	<object>
		<name>checkbox</name>
		<pose>Unspecified</pose>
		<truncated>0</truncated>
		<difficult>0</difficult>
		<bndbox>
			<xmin>35</xmin>
			<ymin>635</ymin>
			<xmax>246</xmax>
			<ymax>687</ymax>
		</bndbox>
	</object>
	<object>
		<name>checkbox</name>
		<pose>Unspecified</pose>
		<truncated>0</truncated>
		<difficult>0</difficult>
		<bndbox>
			<xmin>183</xmin>
			<ymin>635</ymin>
			<xmax>242</xmax>
			<ymax>665</ymax>
		</bndbox>
	</object>
	<object>
		<name>checkbox</name>
		<pose>Unspecified</pose>
		<truncated>0</truncated>
		<difficult>0</difficult>
		<bndbox>
			<xmin>183</xmin>
			<ymin>662</ymin>
			<xmax>235</xmax>
			<ymax>684</ymax>
		</bndbox>
	</object>
	<object>
		<name>checkbox</name>
		<pose>Unspecified</pose>
		<truncated>0</truncated>
		<difficult>0</difficult>
		<bndbox>
			<xmin>179</xmin>
			<ymin>715</ymin>
			<xmax>391</xmax>
			<ymax>742</ymax>
		</bndbox>
	</object>
	<object>
		<name>checkbox</name>
		<pose>Unspecified</pose>
		<truncated>0</truncated>
		<difficult>0</difficult>
		<bndbox>
			<xmin>175</xmin>
			<ymin>740</ymin>
			<xmax>398</xmax>
			<ymax>761</ymax>
		</bndbox>
	</object>
	<object>
		<name>checkbox</name>
		<pose>Unspecified</pose>
		<truncated>0</truncated>
		<difficult>0</difficult>
		<bndbox>
			<xmin>172</xmin>
			<ymin>763</ymin>
			<xmax>394</xmax>
			<ymax>783</ymax>
		</bndbox>
	</object>
</annotation>
